anchor/__init__.py
anchor/app.py
anchor/certificate_ops.py
anchor/cmc.py
anchor/errors.py
anchor/fixups.py
anchor/jsonloader.py
anchor/util.py
anchor/validation.py
anchor/X509/__init__.py
anchor/X509/certificate.py
anchor/X509/errors.py
anchor/X509/extension.py
anchor/X509/name.py
anchor/X509/signature.py
anchor/X509/signing_request.py
anchor/X509/utils.py
anchor/asn1/__init__.py
anchor/asn1/rfc3280.py
anchor/asn1/rfc3281.py
anchor/asn1/rfc3852.py
anchor/asn1/rfc4211.py
anchor/asn1/rfc5280.py
anchor/asn1/rfc5652.py
anchor/asn1/rfc6402.py
anchor/audit/__init__.py
anchor/auth/__init__.py
anchor/auth/keystone.py
anchor/auth/ldap.py
anchor/auth/results.py
anchor/auth/static.py
anchor/controllers/__init__.py
anchor/signers/__init__.py
anchor/signers/cryptography_io.py
anchor/signers/pkcs11.py
anchor/validators/__init__.py
anchor/validators/custom.py
anchor/validators/errors.py
anchor/validators/internal.py
anchor/validators/standards.py
anchor/validators/utils.py
anchor-0.4.0.data/data/etc/anchor/config.json
anchor-0.4.0.data/data/etc/anchor/config.py
anchor-0.4.0.data/scripts/anchor_debug
anchor-0.4.0.data/scripts/anchor_production
anchor-0.4.0.dist-info/DESCRIPTION.rst
anchor-0.4.0.dist-info/METADATA
anchor-0.4.0.dist-info/RECORD
anchor-0.4.0.dist-info/WHEEL
anchor-0.4.0.dist-info/entry_points.txt
anchor-0.4.0.dist-info/metadata.json
anchor-0.4.0.dist-info/pbr.json
anchor-0.4.0.dist-info/top_level.txt
