Metadata-Version: 2.0
Name: anchor
Version: 0.4.0
Summary: Webservice to auto-sign certificates for short amount of time
Home-page: https://wiki.openstack.org/wiki/Security/Projects/Anchor
Author: OpenStack Security Group
Author-email: openstack-dev@lists.openstack.org
License: UNKNOWN
Platform: UNKNOWN
Classifier: Environment :: OpenStack
Classifier: Intended Audience :: Information Technology
Classifier: Intended Audience :: System Administrators
Classifier: Intended Audience :: Developers
Classifier: License :: OSI Approved :: Apache Software License
Classifier: Operating System :: POSIX :: Linux
Classifier: Operating System :: MacOS :: MacOS X
Classifier: Programming Language :: Python
Classifier: Programming Language :: Python :: 2
Classifier: Programming Language :: Python :: 2.7
Classifier: Programming Language :: Python :: 3
Classifier: Programming Language :: Python :: 3.4
Classifier: Topic :: Security
Requires-Dist: Paste
Requires-Dist: WebOb (>=1.2.3)
Requires-Dist: cryptography (>=1.0)
Requires-Dist: ldap3 (>=0.9.8.2)
Requires-Dist: netaddr (>=0.7.12,!=0.7.16)
Requires-Dist: oslo.config (>=3.7.0)
Requires-Dist: oslo.messaging (>=4.0.0)
Requires-Dist: oslo.utils (>=3.5.0)
Requires-Dist: pecan (>=1.0.0)
Requires-Dist: pyasn1
Requires-Dist: pyasn1-modules
Requires-Dist: pycadf (>=1.1.0,!=2.0.0)
Requires-Dist: requests (>=2.8.1,!=2.9.0)
Requires-Dist: stevedore (>=1.5.0)
